autodoc/__about__.py
autodoc/__init__.py
autodoc/__main__.py
autodoc/analyzer.enrichment.md
autodoc/analyzer.py
autodoc/api_server.enrichment.md
autodoc/api_server.py
autodoc/autodoc.enrichment.md
autodoc/autodoc.py
autodoc/chromadb_embedder.enrichment.md
autodoc/chromadb_embedder.py
autodoc/cli.enrichment.md
autodoc/cli.py
autodoc/collaboration_ui.py
autodoc/config.enrichment.md
autodoc/config.py
autodoc/embedder.enrichment.md
autodoc/embedder.py
autodoc/enrichment.enrichment.md
autodoc/enrichment.py
autodoc/graph.enrichment.md
autodoc/graph.py
autodoc/inline_enrichment.enrichment.md
autodoc/inline_enrichment.py
autodoc/local_graph.enrichment.md
autodoc/local_graph.py
autodoc/makefile_parser.enrichment.md
autodoc/makefile_parser.py
autodoc/mcp_server.py
autodoc/ot_engine.py
autodoc/project_analyzer.enrichment.md
autodoc/project_analyzer.py
autodoc/rust_analyzer.enrichment.md
autodoc/rust_analyzer.py
autodoc/summary.enrichment.md
autodoc/summary.py
autodoc/typescript_analyzer.enrichment.md
autodoc/typescript_analyzer.py
ai_code_autodoc-0.7.0.dist-info/METADATA
ai_code_autodoc-0.7.0.dist-info/WHEEL
ai_code_autodoc-0.7.0.dist-info/entry_points.txt
ai_code_autodoc-0.7.0.dist-info/licenses/LICENSE
ai_code_autodoc-0.7.0.dist-info/RECORD
