Metadata-Version: 2.4
Name: ai-code-autodoc
Version: 0.7.0
Summary: AI-powered code intelligence tool for analyzing and documenting codebases
Author: Autodoc Contributors
License: MIT
License-File: LICENSE
Keywords: ai,code-analysis,documentation,embeddings,semantic-search
Classifier: Development Status :: 4 - Beta
Classifier: Intended Audience :: Developers
Classifier: License :: OSI Approved :: MIT License
Classifier: Programming Language :: Python :: 3
Classifier: Programming Language :: Python :: 3.10
Classifier: Programming Language :: Python :: 3.11
Classifier: Programming Language :: Python :: 3.12
Classifier: Topic :: Software Development :: Documentation
Classifier: Topic :: Software Development :: Libraries :: Python Modules
Requires-Python: >=3.10
Requires-Dist: aiohttp-cors>=0.7.0
Requires-Dist: aiohttp>=3.9.1
Requires-Dist: astroid>=3.0.2
Requires-Dist: asyncpg>=0.29.0
Requires-Dist: chromadb>=0.4.0
Requires-Dist: click>=8.1.7
Requires-Dist: fastmcp>=2.14.1
Requires-Dist: numpy<2.0
Requires-Dist: openai>=1.6.1
Requires-Dist: pydantic>=2.0.0
Requires-Dist: pygithub>=2.1.1
Requires-Dist: python-dotenv>=1.0.0
Requires-Dist: pyyaml>=6.0.1
Requires-Dist: rich>=13.7.0
Requires-Dist: sentence-transformers>=2.2.0
Requires-Dist: tenacity>=8.2.0
Requires-Dist: tiktoken>=0.5.2
Requires-Dist: tree-sitter-languages>=1.10.0
Requires-Dist: watchdog>=3.0.0
Provides-Extra: dev
Requires-Dist: black>=23.12.1; extra == 'dev'
Requires-Dist: pytest-asyncio>=0.21.1; extra == 'dev'
Requires-Dist: pytest>=7.4.3; extra == 'dev'
Requires-Dist: ruff>=0.1.8; extra == 'dev'
Provides-Extra: graph
Requires-Dist: matplotlib>=3.8.0; extra == 'graph'
Requires-Dist: neo4j>=5.15.0; extra == 'graph'
Requires-Dist: networkx>=3.2.1; extra == 'graph'
Requires-Dist: plotly>=5.17.0; extra == 'graph'
Requires-Dist: pyvis>=0.3.2; extra == 'graph'
